scrapelib/__init__.py
scrapelib/__main__.py
scrapelib/_types.py
scrapelib/cache.py
scrapelib/py.typed
scrapelib/tests/__init__.py
scrapelib/tests/test_cache.py
scrapelib/tests/test_scraper.py
scrapelib-2.4.1.dist-info/METADATA
scrapelib-2.4.1.dist-info/WHEEL
scrapelib-2.4.1.dist-info/entry_points.txt
scrapelib-2.4.1.dist-info/licenses/LICENSE
scrapelib-2.4.1.dist-info/RECORD
