Metadata-Version: 2.4
Name: scrapelib
Version: 2.4.1
Project-URL: Repository, https://codeberg.org/jpt/scrapelib
Author-email: James Turk <dev@jpt.sh>
License: BSD-2-Clause
License-File: LICENSE
Classifier: Development Status :: 6 - Mature
Classifier: Intended Audience :: Developers
Classifier: License :: OSI Approved :: BSD License
Classifier: Natural Language :: English
Classifier: Operating System :: OS Independent
Classifier: Programming Language :: Python :: 3.9
Classifier: Programming Language :: Python :: 3.10
Classifier: Programming Language :: Python :: 3.11
Classifier: Programming Language :: Python :: 3.12
Classifier: Programming Language :: Python :: 3.13
Classifier: Topic :: Software Development :: Libraries :: Python Modules
Requires-Python: >=3.9
Requires-Dist: requests[security]>=2.28.1
Requires-Dist: urllib3
Provides-Extra: dev
Requires-Dist: coveralls>=3.3.1; extra == 'dev'
Requires-Dist: flake8>=3.9.0; extra == 'dev'
Requires-Dist: flask==2.1.0; extra == 'dev'
Requires-Dist: importlib-metadata<5.0; extra == 'dev'
Requires-Dist: mkdocs-material>=9.2.7; extra == 'dev'
Requires-Dist: mkdocstrings==0.19.0; extra == 'dev'
Requires-Dist: mock>=4.0.3; extra == 'dev'
Requires-Dist: mypy>=0.961; extra == 'dev'
Requires-Dist: pytest-cov>=2.11.1; extra == 'dev'
Requires-Dist: pytest-httpbin>=2.0.0; extra == 'dev'
Requires-Dist: pytest>=7.1.2; extra == 'dev'
Requires-Dist: types-mock>=4.0.15; extra == 'dev'
Requires-Dist: types-requests>=2.28.11; extra == 'dev'
Requires-Dist: werkzeug==2.0.3; extra == 'dev'
